[
  {
    "ISO3166A2":"AF",
    "ISO3166A3":"AFG",
    "ISO3166N3":4,
    "latitude":33,
    "longitude":65,
    "DescripcionESP":"Afganistan",
    "DescripcionING":"Afghanistan",
    "Continente":4
  },
  {
    "ISO3166A2":"AL",
    "ISO3166A3":"ALB",
    "ISO3166N3":8,
    "latitude":41,
    "longitude":20,
    "DescripcionESP":"Albania",
    "DescripcionING":"Albania",
    "Continente":3
  },
  {
    "ISO3166A2":"DZ",
    "ISO3166A3":"DZA",
    "ISO3166N3":12,
    "latitude":28,
    "longitude":3,
    "DescripcionESP":"Argelia",
    "DescripcionING":"Algeria",
    "Continente":5
  },
  {
    "ISO3166A2":"AS",
    "ISO3166A3":"ASM",
    "ISO3166N3":16,
    "latitude":-14.3333333333,
    "longitude":-170,
    "DescripcionESP":"Samoa Americana",
    "DescripcionING":"American Samoa",
    "Continente":2
  },
  {
    "ISO3166A2":"AD",
    "ISO3166A3":"AND",
    "ISO3166N3":20,
    "latitude":42.5,
    "longitude":1.5,
    "DescripcionESP":"Andorra",
    "DescripcionING":"Andorra",
    "Continente":3
  },
  {
    "ISO3166A2":"AO",
    "ISO3166A3":"AGO",
    "ISO3166N3":24,
    "latitude":-12.5,
    "longitude":18.5,
    "DescripcionESP":"Angola",
    "DescripcionING":"Angola",
    "Continente":5
  },
  {
    "ISO3166A2":"AI",
    "ISO3166A3":"AIA",
    "ISO3166N3":660,
    "latitude":18.25,
    "longitude":-63.1666666667,
    "DescripcionESP":"Anguilla",
    "DescripcionING":"Anguilla",
    "Continente":6
  },
  {
    "ISO3166A2":"AG",
    "ISO3166A3":"ATG",
    "ISO3166N3":28,
    "latitude":17.05,
    "longitude":-61.8,
    "DescripcionESP":"Antigua y Barbuda",
    "DescripcionING":"Antigua and Barbuda",
    "Continente":1
  },
  {
    "ISO3166A2":"AR",
    "ISO3166A3":"ARG",
    "ISO3166N3":32,
    "latitude":-34,
    "longitude":-64,
    "DescripcionESP":"Argentina",
    "DescripcionING":"Argentina",
    "Continente":1
  },
  {
    "ISO3166A2":"AM",
    "ISO3166A3":"ARM",
    "ISO3166N3":51,
    "latitude":40,
    "longitude":45,
    "DescripcionESP":"Armenia",
    "DescripcionING":"Armenia",
    "Continente":3
  },
  {
    "ISO3166A2":"AW",
    "ISO3166A3":"ABW",
    "ISO3166N3":533,
    "latitude":12.5,
    "longitude":-69.9666666667,
    "DescripcionESP":"Isla Aruba",
    "DescripcionING":"Aruba",
    "Continente":1
  },
  {
    "ISO3166A2":"AU",
    "ISO3166A3":"AUS",
    "ISO3166N3":36,
    "latitude":-27,
    "longitude":133,
    "DescripcionESP":"Australia",
    "DescripcionING":"Australia",
    "Continente":2
  },
  {
    "ISO3166A2":"AT",
    "ISO3166A3":"AUT",
    "ISO3166N3":40,
    "latitude":47.3333333333,
    "longitude":13.3333333333,
    "DescripcionESP":"Austria",
    "DescripcionING":"Austria",
    "Continente":3
  },
  {
    "ISO3166A2":"AZ",
    "ISO3166A3":"AZE",
    "ISO3166N3":31,
    "latitude":40.5,
    "longitude":47.5,
    "DescripcionESP":"Azserbaijan",
    "DescripcionING":"Azerbaijan",
    "Continente":4
  },
  {
    "ISO3166A2":"BS",
    "ISO3166A3":"BHS",
    "ISO3166N3":44,
    "latitude":24.25,
    "longitude":-76,
    "DescripcionESP":"Bahamas",
    "DescripcionING":"Bahamas",
    "Continente":1
  },
  {
    "ISO3166A2":"BH",
    "ISO3166A3":"BHR",
    "ISO3166N3":48,
    "latitude":26,
    "longitude":50.55,
    "DescripcionESP":"Bahrein",
    "DescripcionING":"Bahrain",
    "Continente":4
  },
  {
    "ISO3166A2":"BD",
    "ISO3166A3":"BGD",
    "ISO3166N3":50,
    "latitude":24,
    "longitude":90,
    "DescripcionESP":"Bangladesh",
    "DescripcionING":"Bangladesh",
    "Continente":4
  },
  {
    "ISO3166A2":"BB",
    "ISO3166A3":"BRB",
    "ISO3166N3":52,
    "latitude":13.1666666667,
    "longitude":-59.5333333333,
    "DescripcionESP":"Barbados",
    "DescripcionING":"Barbados",
    "Continente":1
  },
  {
    "ISO3166A2":"BY",
    "ISO3166A3":"BLR",
    "ISO3166N3":112,
    "latitude":53,
    "longitude":28,
    "DescripcionESP":"Bielorrusia",
    "DescripcionING":"Belarus",
    "Continente":3
  },
  {
    "ISO3166A2":"BE",
    "ISO3166A3":"BEL",
    "ISO3166N3":56,
    "latitude":50.8333333333,
    "longitude":4,
    "DescripcionESP":"Bélgica",
    "DescripcionING":"Belgium",
    "Continente":3
  },
  {
    "ISO3166A2":"BZ",
    "ISO3166A3":"BLZ",
    "ISO3166N3":84,
    "latitude":17.25,
    "longitude":-88.75,
    "DescripcionESP":"Belice",
    "DescripcionING":"Belize",
    "Continente":1
  },
  {
    "ISO3166A2":"BJ",
    "ISO3166A3":"BEN",
    "ISO3166N3":204,
    "latitude":9.5,
    "longitude":2.25,
    "DescripcionESP":"Benin",
    "DescripcionING":"Benin",
    "Continente":5
  },
  {
    "ISO3166A2":"BM",
    "ISO3166A3":"BMU",
    "ISO3166N3":60,
    "latitude":32.3333333333,
    "longitude":-64.75,
    "DescripcionESP":"Bermudas",
    "DescripcionING":"Bermuda",
    "Continente":1
  },
  {
    "ISO3166A2":"BT",
    "ISO3166A3":"BTN",
    "ISO3166N3":64,
    "latitude":27.5,
    "longitude":90.5,
    "DescripcionESP":"Butan",
    "DescripcionING":"Bhutan",
    "Continente":4
  },
  {
    "ISO3166A2":"BO",
    "ISO3166A3":"BOL",
    "ISO3166N3":68,
    "latitude":-17,
    "longitude":-65,
    "DescripcionESP":"Bolivia",
    "DescripcionING":"Bolivia",
    "Continente":1
  },
  {
    "ISO3166A2":"BA",
    "ISO3166A3":"BIH",
    "ISO3166N3":70,
    "latitude":44,
    "longitude":18,
    "DescripcionESP":"Bosnia-Herzegovina",
    "DescripcionING":"Bosnia and Herzegovina",
    "Continente":3
  },
  {
    "ISO3166A2":"BW",
    "ISO3166A3":"BWA",
    "ISO3166N3":72,
    "latitude":-22,
    "longitude":24,
    "DescripcionESP":"Botswana",
    "DescripcionING":"Botswana",
    "Continente":5
  },
  {
    "ISO3166A2":"BR",
    "ISO3166A3":"BRA",
    "ISO3166N3":76,
    "latitude":-10,
    "longitude":-55,
    "DescripcionESP":"Brasil",
    "DescripcionING":"Brazil",
    "Continente":1
  },
  {
    "ISO3166A2":"IO",
    "ISO3166A3":"IOT",
    "ISO3166N3":86,
    "latitude":-6,
    "longitude":71.5,
    "DescripcionESP":"Terr.brit.oc.i",
    "DescripcionING":"British Indian Ocean Territory",
    "Continente":2
  },
  {
    "ISO3166A2":"BN",
    "ISO3166A3":"BRN",
    "ISO3166N3":96,
    "latitude":4.5,
    "longitude":114.666666667,
    "DescripcionESP":"Brunei",
    "DescripcionING":"Brunei Darussalam",
    "Continente":4
  },
  {
    "ISO3166A2":"BG",
    "ISO3166A3":"BGR",
    "ISO3166N3":100,
    "latitude":43,
    "longitude":25,
    "DescripcionESP":"Bulgaria",
    "DescripcionING":"Bulgaria",
    "Continente":3
  },
  {
    "ISO3166A2":"BF",
    "ISO3166A3":"BFA",
    "ISO3166N3":854,
    "latitude":13,
    "longitude":-2,
    "DescripcionESP":"Burkina Faso",
    "DescripcionING":"Burkina Faso",
    "Continente":5
  },
  {
    "ISO3166A2":"BI",
    "ISO3166A3":"BDI",
    "ISO3166N3":108,
    "latitude":-3.5,
    "longitude":30,
    "DescripcionESP":"Burundi",
    "DescripcionING":"Burundi",
    "Continente":5
  },
  {
    "ISO3166A2":"KH",
    "ISO3166A3":"KHM",
    "ISO3166N3":116,
    "latitude":13,
    "longitude":105,
    "DescripcionESP":"Camboya",
    "DescripcionING":"Cambodia",
    "Continente":4
  },
  {
    "ISO3166A2":"CM",
    "ISO3166A3":"CMR",
    "ISO3166N3":120,
    "latitude":6,
    "longitude":12,
    "DescripcionESP":"Camerun",
    "DescripcionING":"Cameroon",
    "Continente":5
  },
  {
    "ISO3166A2":"CA",
    "ISO3166A3":"CAN",
    "ISO3166N3":124,
    "latitude":60,
    "longitude":-95,
    "DescripcionESP":"Canada",
    "DescripcionING":"Canada",
    "Continente":1
  },
  {
    "ISO3166A2":"CV",
    "ISO3166A3":"CPV",
    "ISO3166N3":132,
    "latitude":16,
    "longitude":-24,
    "DescripcionESP":"Cabo Verde",
    "DescripcionING":"Cape Verde",
    "Continente":3
  },
  {
    "ISO3166A2":"KY",
    "ISO3166A3":"CYM",
    "ISO3166N3":136,
    "latitude":19.5,
    "longitude":-80.5,
    "DescripcionESP":"Caiman",
    "DescripcionING":"Cayman Islands",
    "Continente":1
  },
  {
    "ISO3166A2":"CF",
    "ISO3166A3":"CAF",
    "ISO3166N3":140,
    "latitude":7,
    "longitude":21,
    "DescripcionESP":"Rep. Centroafr",
    "DescripcionING":"Central African Republic",
    "Continente":5
  },
  {
    "ISO3166A2":"TD",
    "ISO3166A3":"TCD",
    "ISO3166N3":148,
    "latitude":15,
    "longitude":19,
    "DescripcionESP":"Chad",
    "DescripcionING":"Chad",
    "Continente":5
  },
  {
    "ISO3166A2":"CL",
    "ISO3166A3":"CHL",
    "ISO3166N3":152,
    "latitude":-30,
    "longitude":-71,
    "DescripcionESP":"Chile",
    "DescripcionING":"Chile",
    "Continente":1
  },
  {
    "ISO3166A2":"CN",
    "ISO3166A3":"CHN",
    "ISO3166N3":156,
    "latitude":35,
    "longitude":105,
    "DescripcionESP":"China",
    "DescripcionING":"China",
    "Continente":4
  },
  {
    "ISO3166A2":"CX",
    "ISO3166A3":"CXR",
    "ISO3166N3":162,
    "latitude":-10.5,
    "longitude":105.666666667,
    "DescripcionESP":"Navidad",
    "DescripcionING":"Christmas Island",
    "Continente":2
  },
  {
    "ISO3166A2":"CC",
    "ISO3166A3":"CCK",
    "ISO3166N3":166,
    "latitude":-12.5,
    "longitude":96.8333333333,
    "DescripcionESP":"Cocos Keeling",
    "DescripcionING":"Cocos (keeling) Islands",
    "Continente":6
  },
  {
    "ISO3166A2":"CO",
    "ISO3166A3":"COL",
    "ISO3166N3":170,
    "latitude":4,
    "longitude":-72,
    "DescripcionESP":"Colombia",
    "DescripcionING":"Colombia",
    "Continente":1
  },
  {
    "ISO3166A2":"KM",
    "ISO3166A3":"COM",
    "ISO3166N3":174,
    "latitude":-12.1666666667,
    "longitude":44.25,
    "DescripcionESP":"Comoras",
    "DescripcionING":"Comoros",
    "Continente":6
  },
  {
    "ISO3166A2":"CG",
    "ISO3166A3":"COG",
    "ISO3166N3":178,
    "latitude":-1,
    "longitude":15,
    "DescripcionESP":"Congo (Brazzaville)",
    "DescripcionING":"Congo",
    "Continente":5
  },
  {
    "ISO3166A2":"CK",
    "ISO3166A3":"COK",
    "ISO3166N3":184,
    "latitude":-21.2333333333,
    "longitude":-159.766666667,
    "DescripcionESP":"Cook",
    "DescripcionING":"Cook Islands",
    "Continente":2
  },
  {
    "ISO3166A2":"CR",
    "ISO3166A3":"CRI",
    "ISO3166N3":188,
    "latitude":10,
    "longitude":-84,
    "DescripcionESP":"Costa Rica",
    "DescripcionING":"Costa Rica",
    "Continente":1
  },
  {
    "ISO3166A2":"CI",
    "ISO3166A3":"CIV",
    "ISO3166N3":384,
    "latitude":8,
    "longitude":-5,
    "DescripcionESP":"Costa de Marfil",
    "DescripcionING":"Cote D'ivoire",
    "Continente":5
  },
  {
    "ISO3166A2":"HR",
    "ISO3166A3":"HRV",
    "ISO3166N3":191,
    "latitude":45.1666666667,
    "longitude":15.5,
    "DescripcionESP":"Croacia",
    "DescripcionING":"Croatia",
    "Continente":3
  },
  {
    "ISO3166A2":"CU",
    "ISO3166A3":"CUB",
    "ISO3166N3":192,
    "latitude":21.5,
    "longitude":-80,
    "DescripcionESP":"Cuba",
    "DescripcionING":"Cuba",
    "Continente":1
  },
  {
    "ISO3166A2":"CY",
    "ISO3166A3":"CYP",
    "ISO3166N3":196,
    "latitude":35,
    "longitude":33,
    "DescripcionESP":"Chipre",
    "DescripcionING":"Cyprus",
    "Continente":3
  },
  {
    "ISO3166A2":"CZ",
    "ISO3166A3":"CZE",
    "ISO3166N3":203,
    "latitude":49.75,
    "longitude":15.5,
    "DescripcionESP":"Republica Checa",
    "DescripcionING":"Czech Republic",
    "Continente":3
  },
  {
    "ISO3166A2":"DK",
    "ISO3166A3":"DNK",
    "ISO3166N3":208,
    "latitude":56,
    "longitude":10,
    "DescripcionESP":"Dinamarca",
    "DescripcionING":"Denmark",
    "Continente":3
  },
  {
    "ISO3166A2":"DJ",
    "ISO3166A3":"DJI",
    "ISO3166N3":262,
    "latitude":11.5,
    "longitude":43,
    "DescripcionESP":"Djibouti",
    "DescripcionING":"Djibouti",
    "Continente":6
  },
  {
    "ISO3166A2":"DM",
    "ISO3166A3":"DMA",
    "ISO3166N3":212,
    "latitude":15.4166666667,
    "longitude":-61.3333333333,
    "DescripcionESP":"Dominica",
    "DescripcionING":"Dominica",
    "Continente":1
  },
  {
    "ISO3166A2":"DO",
    "ISO3166A3":"DOM",
    "ISO3166N3":214,
    "latitude":19,
    "longitude":-70.6666666667,
    "DescripcionESP":"Republica Dominicana",
    "DescripcionING":"Dominican Republic",
    "Continente":1
  },
  {
    "ISO3166A2":"EC",
    "ISO3166A3":"ECU",
    "ISO3166N3":218,
    "latitude":-2,
    "longitude":-77.5,
    "DescripcionESP":"Ecuador",
    "DescripcionING":"Ecuador",
    "Continente":1
  },
  {
    "ISO3166A2":"EG",
    "ISO3166A3":"EGY",
    "ISO3166N3":818,
    "latitude":27,
    "longitude":30,
    "DescripcionESP":"Egipto",
    "DescripcionING":"Egypt",
    "Continente":5
  },
  {
    "ISO3166A2":"SV",
    "ISO3166A3":"SLV",
    "ISO3166N3":222,
    "latitude":13.8333333333,
    "longitude":-88.9166666667,
    "DescripcionESP":"El Salvador",
    "DescripcionING":"El Salvador",
    "Continente":1
  },
  {
    "ISO3166A2":"GQ",
    "ISO3166A3":"GNQ",
    "ISO3166N3":226,
    "latitude":2,
    "longitude":10,
    "DescripcionESP":"Guinea Ecuator",
    "DescripcionING":"Equatorial Guinea",
    "Continente":5
  },
  {
    "ISO3166A2":"ER",
    "ISO3166A3":"ERI",
    "ISO3166N3":232,
    "latitude":15,
    "longitude":39,
    "DescripcionESP":"Eritrea",
    "DescripcionING":"Eritrea",
    "Continente":5
  },
  {
    "ISO3166A2":"EE",
    "ISO3166A3":"EST",
    "ISO3166N3":233,
    "latitude":59,
    "longitude":26,
    "DescripcionESP":"Estonia",
    "DescripcionING":"Estonia",
    "Continente":3
  },
  {
    "ISO3166A2":"ET",
    "ISO3166A3":"ETH",
    "ISO3166N3":231,
    "latitude":8,
    "longitude":38,
    "DescripcionESP":"Etiopia",
    "DescripcionING":"Ethiopia",
    "Continente":5
  },
  {
    "ISO3166A2":"FO",
    "ISO3166A3":"FRO",
    "ISO3166N3":234,
    "latitude":62,
    "longitude":-7,
    "DescripcionESP":"Feroe",
    "DescripcionING":"Faroe Islands",
    "Continente":2
  },
  {
    "ISO3166A2":"FJ",
    "ISO3166A3":"FJI",
    "ISO3166N3":242,
    "latitude":-18,
    "longitude":175,
    "DescripcionESP":"Viti Fidji",
    "DescripcionING":"Fiji",
    "Continente":2
  },
  {
    "ISO3166A2":"FI",
    "ISO3166A3":"FIN",
    "ISO3166N3":246,
    "latitude":64,
    "longitude":26,
    "DescripcionESP":"Finlandia",
    "DescripcionING":"Finland",
    "Continente":3
  },
  {
    "ISO3166A2":"FR",
    "ISO3166A3":"FRA",
    "ISO3166N3":250,
    "latitude":46,
    "longitude":2,
    "DescripcionESP":"Francia",
    "DescripcionING":"France",
    "Continente":3
  },
  {
    "ISO3166A2":"GF",
    "ISO3166A3":"GUF",
    "ISO3166N3":254,
    "latitude":4,
    "longitude":-53,
    "DescripcionESP":"Guayana France",
    "DescripcionING":"French Guiana",
    "Continente":1
  },
  {
    "ISO3166A2":"PF",
    "ISO3166A3":"PYF",
    "ISO3166N3":258,
    "latitude":-15,
    "longitude":-140,
    "DescripcionESP":"Polinesia Fran",
    "DescripcionING":"French Polynesia",
    "Continente":2
  },
  {
    "ISO3166A2":"GA",
    "ISO3166A3":"GAB",
    "ISO3166N3":266,
    "latitude":-1,
    "longitude":11.75,
    "DescripcionESP":"Gabon",
    "DescripcionING":"Gabon",
    "Continente":5
  },
  {
    "ISO3166A2":"GM",
    "ISO3166A3":"GMB",
    "ISO3166N3":270,
    "latitude":13.4666666667,
    "longitude":-16.5666666667,
    "DescripcionESP":"Gambia",
    "DescripcionING":"Gambia",
    "Continente":5
  },
  {
    "ISO3166A2":"GE",
    "ISO3166A3":"GEO",
    "ISO3166N3":268,
    "latitude":42,
    "longitude":43.5,
    "DescripcionESP":"Georgia",
    "DescripcionING":"Georgia",
    "Continente":3
  },
  {
    "ISO3166A2":"DE",
    "ISO3166A3":"DEU",
    "ISO3166N3":276,
    "latitude":51,
    "longitude":9,
    "DescripcionESP":"Alemania",
    "DescripcionING":"Germany",
    "Continente":3
  },
  {
    "ISO3166A2":"GH",
    "ISO3166A3":"GHA",
    "ISO3166N3":288,
    "latitude":8,
    "longitude":-2,
    "DescripcionESP":"Ghana",
    "DescripcionING":"Ghana",
    "Continente":5
  },
  {
    "ISO3166A2":"GI",
    "ISO3166A3":"GIB",
    "ISO3166N3":292,
    "latitude":36.1333333333,
    "longitude":-5.35,
    "DescripcionESP":"Gibraltar",
    "DescripcionING":"Gibraltar",
    "Continente":3
  },
  {
    "ISO3166A2":"GR",
    "ISO3166A3":"GRC",
    "ISO3166N3":300,
    "latitude":39,
    "longitude":22,
    "DescripcionESP":"Grecia",
    "DescripcionING":"Greece",
    "Continente":3
  },
  {
    "ISO3166A2":"GL",
    "ISO3166A3":"GRL",
    "ISO3166N3":304,
    "latitude":72,
    "longitude":-40,
    "DescripcionESP":"Groenlandia",
    "DescripcionING":"Greenland",
    "Continente":3
  },
  {
    "ISO3166A2":"GD",
    "ISO3166A3":"GRD",
    "ISO3166N3":308,
    "latitude":12.1166666667,
    "longitude":-61.6666666667,
    "DescripcionESP":"Grenada",
    "DescripcionING":"Grenada",
    "Continente":1
  },
  {
    "ISO3166A2":"GP",
    "ISO3166A3":"GLP",
    "ISO3166N3":312,
    "latitude":16.25,
    "longitude":-61.5833333333,
    "DescripcionESP":"Guadalupe",
    "DescripcionING":"Guadeloupe",
    "Continente":1
  },
  {
    "ISO3166A2":"GU",
    "ISO3166A3":"GUM",
    "ISO3166N3":316,
    "latitude":13.4666666667,
    "longitude":144.783333333,
    "DescripcionESP":"Guam",
    "DescripcionING":"Guam",
    "Continente":2
  },
  {
    "ISO3166A2":"GT",
    "ISO3166A3":"GTM",
    "ISO3166N3":320,
    "latitude":15.5,
    "longitude":-90.25,
    "DescripcionESP":"Guatemala",
    "DescripcionING":"Guatemala",
    "Continente":1
  },
  {
    "ISO3166A2":"GN",
    "ISO3166A3":"GIN",
    "ISO3166N3":324,
    "latitude":11,
    "longitude":-10,
    "DescripcionESP":"Guinea",
    "DescripcionING":"Guinea",
    "Continente":5
  },
  {
    "ISO3166A2":"GW",
    "ISO3166A3":"GNB",
    "ISO3166N3":624,
    "latitude":12,
    "longitude":-15,
    "DescripcionESP":"Guinea-bissau",
    "DescripcionING":"Guinea-bissau",
    "Continente":5
  },
  {
    "ISO3166A2":"GY",
    "ISO3166A3":"GUY",
    "ISO3166N3":328,
    "latitude":5,
    "longitude":-59,
    "DescripcionESP":"Guyana",
    "DescripcionING":"Guyana",
    "Continente":1
  },
  {
    "ISO3166A2":"HT",
    "ISO3166A3":"HTI",
    "ISO3166N3":332,
    "latitude":19,
    "longitude":-72.4166666667,
    "DescripcionESP":"Haiti",
    "DescripcionING":"Haiti",
    "Continente":1
  },
  {
    "ISO3166A2":"VA",
    "ISO3166A3":"VAT",
    "ISO3166N3":336,
    "latitude":41.9,
    "longitude":12.45,
    "DescripcionESP":"Ciudad del vat",
    "DescripcionING":"Vatican City state (holy see)",
    "Continente":3
  },
  {
    "ISO3166A2":"HN",
    "ISO3166A3":"HND",
    "ISO3166N3":340,
    "latitude":15,
    "longitude":-86.5,
    "DescripcionESP":"Honduras",
    "DescripcionING":"Honduras",
    "Continente":1
  },
  {
    "ISO3166A2":"HK",
    "ISO3166A3":"HKG",
    "ISO3166N3":344,
    "latitude":22.25,
    "longitude":114.166666667,
    "DescripcionESP":"Hong Kong",
    "DescripcionING":"Hong Kong",
    "Continente":4
  },
  {
    "ISO3166A2":"HU",
    "ISO3166A3":"HUN",
    "ISO3166N3":348,
    "latitude":47,
    "longitude":20,
    "DescripcionESP":"Hungria",
    "DescripcionING":"Hungary",
    "Continente":3
  },
  {
    "ISO3166A2":"IS",
    "ISO3166A3":"ISL",
    "ISO3166N3":352,
    "latitude":65,
    "longitude":-18,
    "DescripcionESP":"Islandia",
    "DescripcionING":"Iceland",
    "Continente":3
  },
  {
    "ISO3166A2":"IN",
    "ISO3166A3":"IND",
    "ISO3166N3":356,
    "latitude":20,
    "longitude":77,
    "DescripcionESP":"India",
    "DescripcionING":"India",
    "Continente":4
  },
  {
    "ISO3166A2":"ID",
    "ISO3166A3":"IDN",
    "ISO3166N3":360,
    "latitude":-5,
    "longitude":120,
    "DescripcionESP":"Indonesia",
    "DescripcionING":"Indonesia",
    "Continente":4
  },
  {
    "ISO3166A2":"IR",
    "ISO3166A3":"IRN",
    "ISO3166N3":364,
    "latitude":32,
    "longitude":53,
    "DescripcionESP":"Iran",
    "DescripcionING":"Iran (Islamic Republic of)",
    "Continente":4
  },
  {
    "ISO3166A2":"IQ",
    "ISO3166A3":"IRQ",
    "ISO3166N3":368,
    "latitude":33,
    "longitude":44,
    "DescripcionESP":"Irak",
    "DescripcionING":"Iraq",
    "Continente":4
  },
  {
    "ISO3166A2":"IE",
    "ISO3166A3":"IRL",
    "ISO3166N3":372,
    "latitude":53,
    "longitude":-8,
    "DescripcionESP":"Irlanda (eire)",
    "DescripcionING":"Ireland",
    "Continente":3
  },
  {
    "ISO3166A2":"IL",
    "ISO3166A3":"ISR",
    "ISO3166N3":376,
    "latitude":31.5,
    "longitude":34.75,
    "DescripcionESP":"Israel",
    "DescripcionING":"Israel",
    "Continente":4
  },
  {
    "ISO3166A2":"IT",
    "ISO3166A3":"ITA",
    "ISO3166N3":380,
    "latitude":42.8333333333,
    "longitude":12.8333333333,
    "DescripcionESP":"Italia",
    "DescripcionING":"Italy",
    "Continente":3
  },
  {
    "ISO3166A2":"JM",
    "ISO3166A3":"JAM",
    "ISO3166N3":388,
    "latitude":18.25,
    "longitude":-77.5,
    "DescripcionESP":"Jamaica",
    "DescripcionING":"Jamaica",
    "Continente":1
  },
  {
    "ISO3166A2":"JP",
    "ISO3166A3":"JPN",
    "ISO3166N3":392,
    "latitude":36,
    "longitude":138,
    "DescripcionESP":"Japon",
    "DescripcionING":"Japan",
    "Continente":4
  },
  {
    "ISO3166A2":"JO",
    "ISO3166A3":"JOR",
    "ISO3166N3":400,
    "latitude":31,
    "longitude":36,
    "DescripcionESP":"Jordania",
    "DescripcionING":"Jordan",
    "Continente":4
  },
  {
    "ISO3166A2":"KZ",
    "ISO3166A3":"KAZ",
    "ISO3166N3":398,
    "latitude":48,
    "longitude":68,
    "DescripcionESP":"Kasajstan",
    "DescripcionING":"Kazakhstan",
    "Continente":4
  },
  {
    "ISO3166A2":"KE",
    "ISO3166A3":"KEN",
    "ISO3166N3":404,
    "latitude":1,
    "longitude":38,
    "DescripcionESP":"Kenia",
    "DescripcionING":"Kenya",
    "Continente":5
  },
  {
    "ISO3166A2":"KI",
    "ISO3166A3":"KIR",
    "ISO3166N3":296,
    "latitude":1.41666666667,
    "longitude":173,
    "DescripcionESP":"Kiribati",
    "DescripcionING":"Kiribati",
    "Continente":6
  },
  {
    "ISO3166A2":"KP",
    "ISO3166A3":"PRK",
    "ISO3166N3":408,
    "latitude":40,
    "longitude":127,
    "DescripcionESP":"Corea del Norte",
    "DescripcionING":"Korea, Democratic People's Republic of",
    "Continente":4
  },
  {
    "ISO3166A2":"KR",
    "ISO3166A3":"KOR",
    "ISO3166N3":410,
    "latitude":37,
    "longitude":127.5,
    "DescripcionESP":"Corea del Sur",
    "DescripcionING":"Korea, Republic of",
    "Continente":4
  },
  {
    "ISO3166A2":"KW",
    "ISO3166A3":"KWT",
    "ISO3166N3":414,
    "latitude":29.366667,
    "longitude":47.966667,
    "DescripcionESP":"Kuweit",
    "DescripcionING":"Kuwait",
    "Continente":4
  },
  {
    "ISO3166A2":"KG",
    "ISO3166A3":"KGZ",
    "ISO3166N3":417,
    "latitude":41,
    "longitude":75,
    "DescripcionESP":"Kyrgyszstan",
    "DescripcionING":"Kyrgyzstan",
    "Continente":4
  },
  {
    "ISO3166A2":"LA",
    "ISO3166A3":"LAO",
    "ISO3166N3":418,
    "latitude":18,
    "longitude":105,
    "DescripcionESP":"Laos",
    "DescripcionING":"Lao People's Democratic Republic",
    "Continente":4
  },
  {
    "ISO3166A2":"LV",
    "ISO3166A3":"LVA",
    "ISO3166N3":428,
    "latitude":57,
    "longitude":25,
    "DescripcionESP":"Letonia",
    "DescripcionING":"Latvia",
    "Continente":3
  },
  {
    "ISO3166A2":"LB",
    "ISO3166A3":"LBN",
    "ISO3166N3":422,
    "latitude":33.8333333333,
    "longitude":35.8333333333,
    "DescripcionESP":"Libano",
    "DescripcionING":"Lebanon",
    "Continente":4
  },
  {
    "ISO3166A2":"LS",
    "ISO3166A3":"LSO",
    "ISO3166N3":426,
    "latitude":-29.5,
    "longitude":28.5,
    "DescripcionESP":"Lesotho",
    "DescripcionING":"Lesotho",
    "Continente":5
  },
  {
    "ISO3166A2":"LR",
    "ISO3166A3":"LBR",
    "ISO3166N3":430,
    "latitude":6.5,
    "longitude":-9.5,
    "DescripcionESP":"Liberia",
    "DescripcionING":"Liberia",
    "Continente":5
  },
  {
    "ISO3166A2":"LY",
    "ISO3166A3":"LBY",
    "ISO3166N3":434,
    "latitude":25,
    "longitude":17,
    "DescripcionESP":"Libia",
    "DescripcionING":"Libyan Arab Jamahiriya",
    "Continente":5
  },
  {
    "ISO3166A2":"LI",
    "ISO3166A3":"LIE",
    "ISO3166N3":438,
    "latitude":47.2666666667,
    "longitude":9.53333333333,
    "DescripcionESP":"Liechtenstein",
    "DescripcionING":"Liechtenstein",
    "Continente":3
  },
  {
    "ISO3166A2":"LT",
    "ISO3166A3":"LTU",
    "ISO3166N3":440,
    "latitude":56,
    "longitude":24,
    "DescripcionESP":"Lituania",
    "DescripcionING":"Lithuania",
    "Continente":3
  },
  {
    "ISO3166A2":"LU",
    "ISO3166A3":"LUX",
    "ISO3166N3":442,
    "latitude":49.75,
    "longitude":6.16666666667,
    "DescripcionESP":"Luxemburgo",
    "DescripcionING":"Luxemburg",
    "Continente":3
  },
  {
    "ISO3166A2":"MO",
    "ISO3166A3":"MAC",
    "ISO3166N3":446,
    "latitude":22.1666666667,
    "longitude":113.55,
    "DescripcionESP":"Macao",
    "DescripcionING":"Macau",
    "Continente":4
  },
  {
    "ISO3166A2":"MK",
    "ISO3166A3":"MKD",
    "ISO3166N3":807,
    "latitude":41.8333333333,
    "longitude":22,
    "DescripcionESP":"Macedonia",
    "DescripcionING":"Macedonia, The Former Yugoslav Republic of",
    "Continente":3
  },
    {
        "ISO3166A2":"SR",
        "ISO3166A3":"SRB",
        "ISO3166N3":688,
        "latitude":44.48,
        "longitude":20.28,
        "DescripcionESP":"Serbia",
        "DescripcionING":"Serbia",
        "Continente":3
    },
  {
    "ISO3166A2":"MG",
    "ISO3166A3":"MDG",
    "ISO3166N3":450,
    "latitude":-20,
    "longitude":47,
    "DescripcionESP":"Madagascar",
    "DescripcionING":"Madagascar",
    "Continente":5
  },
  {
    "ISO3166A2":"MW",
    "ISO3166A3":"MWI",
    "ISO3166N3":454,
    "latitude":-13.5,
    "longitude":34,
    "DescripcionESP":"Malawi",
    "DescripcionING":"Malawi",
    "Continente":5
  },
  {
    "ISO3166A2":"MY",
    "ISO3166A3":"MYS",
    "ISO3166N3":458,
    "latitude":2.5,
    "longitude":112.5,
    "DescripcionESP":"Malasia",
    "DescripcionING":"Malaysia",
    "Continente":4
  },
  {
    "ISO3166A2":"MV",
    "ISO3166A3":"MDV",
    "ISO3166N3":462,
    "latitude":3.25,
    "longitude":73,
    "DescripcionESP":"Maldivas",
    "DescripcionING":"Maldives",
    "Continente":6
  },
  {
    "ISO3166A2":"ML",
    "ISO3166A3":"MLI",
    "ISO3166N3":466,
    "latitude":17,
    "longitude":-4,
    "DescripcionESP":"Mali",
    "DescripcionING":"Mali",
    "Continente":5
  },
  {
    "ISO3166A2":"MT",
    "ISO3166A3":"MLT",
    "ISO3166N3":470,
    "latitude":35.8333333333,
    "longitude":14.5833333333,
    "DescripcionESP":"Malta",
    "DescripcionING":"Malta",
    "Continente":3
  },
  {
    "ISO3166A2":"MH",
    "ISO3166A3":"MHL",
    "ISO3166N3":584,
    "latitude":9,
    "longitude":168,
    "DescripcionESP":"Islas Marshall",
    "DescripcionING":"Marshall Islands",
    "Continente":2
  },
  {
    "ISO3166A2":"MQ",
    "ISO3166A3":"MTQ",
    "ISO3166N3":474,
    "latitude":14.6,
    "longitude":-61.0833333333,
    "DescripcionESP":"Martinica",
    "DescripcionING":"Martinique",
    "Continente":1
  },
  {
    "ISO3166A2":"MR",
    "ISO3166A3":"MRT",
    "ISO3166N3":478,
    "latitude":20,
    "longitude":-12,
    "DescripcionESP":"Mauritania",
    "DescripcionING":"Mauritania",
    "Continente":5
  },
  {
    "ISO3166A2":"MU",
    "ISO3166A3":"MUS",
    "ISO3166N3":480,
    "latitude":-20.2833333333,
    "longitude":57.55,
    "DescripcionESP":"Mauricio",
    "DescripcionING":"Mauritius",
    "Continente":5
  },
  {
    "ISO3166A2":"YT",
    "ISO3166A3":"MYT",
    "ISO3166N3":175,
    "latitude":-12.8333333333,
    "longitude":45.1666666667,
    "DescripcionESP":"Mayotte",
    "DescripcionING":"Mayotte",
    "Continente":6
  },
  {
    "ISO3166A2":"MX",
    "ISO3166A3":"MEX",
    "ISO3166N3":484,
    "latitude":23,
    "longitude":-102,
    "DescripcionESP":"Mexico",
    "DescripcionING":"Mexico",
    "Continente":1
  },
  {
    "ISO3166A2":"FM",
    "ISO3166A3":"FSM",
    "ISO3166N3":583,
    "latitude":6.91666666667,
    "longitude":158.25,
    "DescripcionESP":"Micronesia Est",
    "DescripcionING":"Micronesia, federated states of",
    "Continente":2
  },
  {
    "ISO3166A2":"MD",
    "ISO3166A3":"MDA",
    "ISO3166N3":498,
    "latitude":47,
    "longitude":29,
    "DescripcionESP":"Moldavia",
    "DescripcionING":"Moldova, Republic of",
    "Continente":3
  },
  {
    "ISO3166A2":"MC",
    "ISO3166A3":"MCO",
    "ISO3166N3":492,
    "latitude":43.732778,
    "longitude":7.419722,
    "DescripcionESP":"Monaco",
    "DescripcionING":"Monaco",
    "Continente":3
  },
  {
    "ISO3166A2":"MN",
    "ISO3166A3":"MNG",
    "ISO3166N3":496,
    "latitude":46,
    "longitude":105,
    "DescripcionESP":"Mongolia Rep.P",
    "DescripcionING":"Mongolia",
    "Continente":4
  },
  {
    "ISO3166A2":"MS",
    "ISO3166A3":"MSR",
    "ISO3166N3":500,
    "latitude":16.75,
    "longitude":-62.2,
    "DescripcionESP":"Montserrat",
    "DescripcionING":"Montserrat",
    "Continente":1
  },
  {
    "ISO3166A2":"MA",
    "ISO3166A3":"MAR",
    "ISO3166N3":504,
    "latitude":32,
    "longitude":-5,
    "DescripcionESP":"Marruecos",
    "DescripcionING":"Morocco",
    "Continente":5
  },
  {
    "ISO3166A2":"MZ",
    "ISO3166A3":"MOZ",
    "ISO3166N3":508,
    "latitude":-18.25,
    "longitude":35,
    "DescripcionESP":"Mozambique",
    "DescripcionING":"Mozambique",
    "Continente":5
  },
  {
    "ISO3166A2":"MM",
    "ISO3166A3":"MMR",
    "ISO3166N3":104,
    "latitude":22,
    "longitude":98,
    "DescripcionESP":"Myanmar",
    "DescripcionING":"Myanmar",
    "Continente":4
  },
  {
    "ISO3166A2":"NA",
    "ISO3166A3":"NAM",
    "ISO3166N3":516,
    "latitude":-22,
    "longitude":17,
    "DescripcionESP":"Namibia",
    "DescripcionING":"Namibia",
    "Continente":5
  },
  {
    "ISO3166A2":"NR",
    "ISO3166A3":"NRU",
    "ISO3166N3":520,
    "latitude":-0.533333333333,
    "longitude":166.916666667,
    "DescripcionESP":"Nauru",
    "DescripcionING":"Nauru",
    "Continente":2
  },
  {
    "ISO3166A2":"NP",
    "ISO3166A3":"NPL",
    "ISO3166N3":524,
    "latitude":28,
    "longitude":84,
    "DescripcionESP":"Nepal",
    "DescripcionING":"Nepal",
    "Continente":4
  },
  {
    "ISO3166A2":"NL",
    "ISO3166A3":"NLD",
    "ISO3166N3":528,
    "latitude":52.5,
    "longitude":5.75,
    "DescripcionESP":"Paises Bajos",
    "DescripcionING":"Netherlands",
    "Continente":3
  },
  {
    "ISO3166A2":"NC",
    "ISO3166A3":"NCL",
    "ISO3166N3":540,
    "latitude":-21.5,
    "longitude":165.5,
    "DescripcionESP":"Nueva Caledonia",
    "DescripcionING":"New Caledonia",
    "Continente":6
  },
  {
    "ISO3166A2":"NZ",
    "ISO3166A3":"NZL",
    "ISO3166N3":554,
    "latitude":-41,
    "longitude":174,
    "DescripcionESP":"Nueva Zelanda",
    "DescripcionING":"New Zealand",
    "Continente":2
  },
  {
    "ISO3166A2":"NI",
    "ISO3166A3":"NIC",
    "ISO3166N3":558,
    "latitude":13,
    "longitude":-85,
    "DescripcionESP":"Nicaragua",
    "DescripcionING":"Nicaragua",
    "Continente":1
  },
  {
    "ISO3166A2":"NE",
    "ISO3166A3":"NER",
    "ISO3166N3":562,
    "latitude":16,
    "longitude":8,
    "DescripcionESP":"Niger",
    "DescripcionING":"Niger",
    "Continente":5
  },
  {
    "ISO3166A2":"NG",
    "ISO3166A3":"NGA",
    "ISO3166N3":566,
    "latitude":10,
    "longitude":8,
    "DescripcionESP":"Nigeria",
    "DescripcionING":"Nigeria",
    "Continente":5
  },
  {
    "ISO3166A2":"NU",
    "ISO3166A3":"NIU",
    "ISO3166N3":570,
    "latitude":-19.0333333333,
    "longitude":-169.866666667,
    "DescripcionESP":"Niue",
    "DescripcionING":"Niue",
    "Continente":2
  },
  {
    "ISO3166A2":"NF",
    "ISO3166A3":"NFK",
    "ISO3166N3":574,
    "latitude":-29.0333333333,
    "longitude":167.95,
    "DescripcionESP":"Norfolk",
    "DescripcionING":"Norfolk Island",
    "Continente":2
  },
  {
    "ISO3166A2":"NO",
    "ISO3166A3":"NOR",
    "ISO3166N3":578,
    "latitude":62,
    "longitude":10,
    "DescripcionESP":"Noruega",
    "DescripcionING":"Norway",
    "Continente":3
  },
  {
    "ISO3166A2":"PS",
    "ISO3166A3":"PSE",
    "ISO3166N3":275,
    "latitude":32,
    "longitude":35.25,
    "DescripcionESP":"Palestina Z.Ne",
    "DescripcionING":"Neutral Zone",
    "Continente":4
  },
  {
    "ISO3166A2":"OM",
    "ISO3166A3":"OMN",
    "ISO3166N3":512,
    "latitude":21,
    "longitude":57,
    "DescripcionESP":"Oman",
    "DescripcionING":"Oman",
    "Continente":4
  },
  {
    "ISO3166A2":"PK",
    "ISO3166A3":"PAK",
    "ISO3166N3":586,
    "latitude":30,
    "longitude":70,
    "DescripcionESP":"Pakistan",
    "DescripcionING":"Pakistan",
    "Continente":4
  },
  {
    "ISO3166A2":"PW",
    "ISO3166A3":"PLW",
    "ISO3166N3":585,
    "latitude":7.5,
    "longitude":134.5,
    "DescripcionESP":"Palau",
    "DescripcionING":"Palau",
    "Continente":2
  },
  {
    "ISO3166A2":"PA",
    "ISO3166A3":"PAN",
    "ISO3166N3":591,
    "latitude":9,
    "longitude":-80,
    "DescripcionESP":"Panamá",
    "DescripcionING":"Panama",
    "Continente":1
  },
  {
    "ISO3166A2":"PG",
    "ISO3166A3":"PNG",
    "ISO3166N3":598,
    "latitude":-6,
    "longitude":147,
    "DescripcionESP":"Papua Nueva Guinea",
    "DescripcionING":"Papua New Guinea",
    "Continente":2
  },
  {
    "ISO3166A2":"PY",
    "ISO3166A3":"PRY",
    "ISO3166N3":600,
    "latitude":-23,
    "longitude":-58,
    "DescripcionESP":"Paraguay",
    "DescripcionING":"Paraguay",
    "Continente":1
  },
  {
    "ISO3166A2":"PE",
    "ISO3166A3":"PER",
    "ISO3166N3":604,
    "latitude":-10,
    "longitude":-76,
    "DescripcionESP":"Peru",
    "DescripcionING":"Peru",
    "Continente":1
  },
  {
    "ISO3166A2":"PH",
    "ISO3166A3":"PHL",
    "ISO3166N3":608,
    "latitude":13,
    "longitude":122,
    "DescripcionESP":"Filipinas",
    "DescripcionING":"Philippines",
    "Continente":4
  },
  {
    "ISO3166A2":"PN",
    "ISO3166A3":"PCN",
    "ISO3166N3":612,
    "latitude":-25.0666666667,
    "longitude":-130.1,
    "DescripcionESP":"Pitcairn",
    "DescripcionING":"Pitcairn",
    "Continente":2
  },
  {
    "ISO3166A2":"PL",
    "ISO3166A3":"POL",
    "ISO3166N3":616,
    "latitude":52,
    "longitude":20,
    "DescripcionESP":"Polonia",
    "DescripcionING":"Poland",
    "Continente":3
  },
  {
    "ISO3166A2":"PT",
    "ISO3166A3":"PRT",
    "ISO3166N3":620,
    "latitude":39.5,
    "longitude":-8,
    "DescripcionESP":"Portugal",
    "DescripcionING":"Portugal",
    "Continente":3
  },
  {
    "ISO3166A2":"PR",
    "ISO3166A3":"PRI",
    "ISO3166N3":630,
    "latitude":18.25,
    "longitude":-66.5,
    "DescripcionESP":"Puerto Rico",
    "DescripcionING":"Puerto Rico",
    "Continente":1
  },
  {
    "ISO3166A2":"QA",
    "ISO3166A3":"QAT",
    "ISO3166N3":634,
    "latitude":25.5,
    "longitude":51.25,
    "DescripcionESP":"Qatar",
    "DescripcionING":"Qatar",
    "Continente":4
  },
  {
    "ISO3166A2":"RE",
    "ISO3166A3":"REU",
    "ISO3166N3":638,
    "latitude":-21.1,
    "longitude":55.6,
    "DescripcionESP":"Reunion",
    "DescripcionING":"Reunion",
    "Continente":2
  },
  {
    "ISO3166A2":"RO",
    "ISO3166A3":"ROU",
    "ISO3166N3":642,
    "latitude":46,
    "longitude":25,
    "DescripcionESP":"Rumania",
    "DescripcionING":"Romania",
    "Continente":3
  },
    {
    "ISO3166A2":"RO",
    "ISO3166A3":"ROM",
    "ISO3166N3":642,
    "latitude":46,
    "longitude":25,
    "DescripcionESP":"Rumania",
    "DescripcionING":"Romania",
    "Continente":3
  },
  {
    "ISO3166A2":"RU",
    "ISO3166A3":"RUS",
    "ISO3166N3":643,
    "latitude":60,
    "longitude":100,
    "DescripcionESP":"Rusia",
    "DescripcionING":"Russian Federation",
    "Continente":3
  },
  {
    "ISO3166A2":"RW",
    "ISO3166A3":"RWA",
    "ISO3166N3":646,
    "latitude":-2,
    "longitude":30,
    "DescripcionESP":"Rwanda",
    "DescripcionING":"Rwanda",
    "Continente":5
  },
  {
    "ISO3166A2":"SH",
    "ISO3166A3":"SHN",
    "ISO3166N3":654,
    "latitude":-15.95,
    "longitude":-5.7,
    "DescripcionESP":"Santa Elena",
    "DescripcionING":"St. Helena",
    "Continente":6
  },
  {
    "ISO3166A2":"KN",
    "ISO3166A3":"KNA",
    "ISO3166N3":659,
    "latitude":17.3333333333,
    "longitude":-62.75,
    "DescripcionESP":"St. Kitts y Nevis",
    "DescripcionING":"Saint Kitts and Nevis",
    "Continente":1
  },
  {
    "ISO3166A2":"LC",
    "ISO3166A3":"LCA",
    "ISO3166N3":662,
    "latitude":13.8833333333,
    "longitude":-60.9666666667,
    "DescripcionESP":"Santa Lucia",
    "DescripcionING":"Saint Lucia",
    "Continente":1
  },
  {
    "ISO3166A2":"PM",
    "ISO3166A3":"SPM",
    "ISO3166N3":666,
    "latitude":46.8333333333,
    "longitude":-56.3333333333,
    "DescripcionESP":"San Pedro y Mi",
    "DescripcionING":"St. Pierre and Miquelon",
    "Continente":6
  },
  {
    "ISO3166A2":"VC",
    "ISO3166A3":"VCT",
    "ISO3166N3":670,
    "latitude":13.25,
    "longitude":-61.2,
    "DescripcionESP":"San Vicente y las Granadinas",
    "DescripcionING":"Saint Vincent and the Grenadines",
    "Continente":1
  },
  {
    "ISO3166A2":"WS",
    "ISO3166A3":"WSM",
    "ISO3166N3":882,
    "latitude":-13.5833333333,
    "longitude":-172.333333333,
    "DescripcionESP":"Samoa",
    "DescripcionING":"Samoa",
    "Continente":2
  },
  {
    "ISO3166A2":"SM",
    "ISO3166A3":"SMR",
    "ISO3166N3":674,
    "latitude":43.933333,
    "longitude":12.4166666667,
    "DescripcionESP":"San Marino",
    "DescripcionING":"San Marino",
    "Continente":6
  },
  {
    "ISO3166A2":"ST",
    "ISO3166A3":"STP",
    "ISO3166N3":678,
    "latitude":1,
    "longitude":7,
    "DescripcionESP":"S.Tome y Princ",
    "DescripcionING":"Sao Tome and Principe",
    "Continente":5
  },
  {
    "ISO3166A2":"SA",
    "ISO3166A3":"SAU",
    "ISO3166N3":682,
    "latitude":25,
    "longitude":45,
    "DescripcionESP":"Arabia Saudita",
    "DescripcionING":"Saudi Arabia",
    "Continente":4
  },
  {
    "ISO3166A2":"SN",
    "ISO3166A3":"SEN",
    "ISO3166N3":686,
    "latitude":14,
    "longitude":-14,
    "DescripcionESP":"Senegal",
    "DescripcionING":"Senegal",
    "Continente":5
  },
  {
    "ISO3166A2":"SC",
    "ISO3166A3":"SYC",
    "ISO3166N3":690,
    "latitude":-4.58333333333,
    "longitude":55.6666666667,
    "DescripcionESP":"Seychelles",
    "DescripcionING":"Seychelles",
    "Continente":5
  },
  {
    "ISO3166A2":"SL",
    "ISO3166A3":"SLE",
    "ISO3166N3":694,
    "latitude":8.5,
    "longitude":-11.5,
    "DescripcionESP":"Sierra Leona",
    "DescripcionING":"Sierra Leone",
    "Continente":5
  },
  {
    "ISO3166A2":"SG",
    "ISO3166A3":"SGP",
    "ISO3166N3":702,
    "latitude":1.36666666667,
    "longitude":103.8,
    "DescripcionESP":"Singapur",
    "DescripcionING":"Singapore",
    "Continente":4
  },
  {
    "ISO3166A2":"SK",
    "ISO3166A3":"SVK",
    "ISO3166N3":703,
    "latitude":48.6666666667,
    "longitude":19.5,
    "DescripcionESP":"Eslovaquia",
    "DescripcionING":"Slovakia (Slovak Republic)",
    "Continente":3
  },
  {
    "ISO3166A2":"SI",
    "ISO3166A3":"SVN",
    "ISO3166N3":705,
    "latitude":46.1166666667,
    "longitude":14.8166666667,
    "DescripcionESP":"Eslovenia",
    "DescripcionING":"Slovenia",
    "Continente":3
  },
  {
    "ISO3166A2":"SB",
    "ISO3166A3":"SLB",
    "ISO3166N3":90,
    "latitude":-8,
    "longitude":159,
    "DescripcionESP":"Salomon",
    "DescripcionING":"Solomon Islands",
    "Continente":2
  },
  {
    "ISO3166A2":"SO",
    "ISO3166A3":"SOM",
    "ISO3166N3":706,
    "latitude":10,
    "longitude":49,
    "DescripcionESP":"Somalia",
    "DescripcionING":"Somalia",
    "Continente":5
  },
  {
    "ISO3166A2":"ZA",
    "ISO3166A3":"ZAF",
    "ISO3166N3":710,
    "latitude":-29,
    "longitude":24,
    "DescripcionESP":"Republica de Sudafrica",
    "DescripcionING":"South Africa",
    "Continente":5
  },
  {
    "ISO3166A2":"ES",
    "ISO3166A3":"ESP",
    "ISO3166N3":724,
    "latitude":40,
    "longitude":-4,
    "DescripcionESP":"España",
    "DescripcionING":"Spain",
    "Continente":3
  },
  {
    "ISO3166A2":"LK",
    "ISO3166A3":"LKA",
    "ISO3166N3":144,
    "latitude":7,
    "longitude":81,
    "DescripcionESP":"Sri Lanka",
    "DescripcionING":"Sri Lanka",
    "Continente":4
  },
  {
    "ISO3166A2":"SD",
    "ISO3166A3":"SDN",
    "ISO3166N3":729,
    "latitude":15,
    "longitude":30,
    "DescripcionESP":"Sudan",
    "DescripcionING":"Sudan",
    "Continente":5
  },
  {
    "ISO3166A2":"SR",
    "ISO3166A3":"SUR",
    "ISO3166N3":740,
    "latitude":4,
    "longitude":-56,
    "DescripcionESP":"Surinam",
    "DescripcionING":"Suriname",
    "Continente":1
  },
  {
    "ISO3166A2":"SZ",
    "ISO3166A3":"SWZ",
    "ISO3166N3":748,
    "latitude":-26.5,
    "longitude":31.5,
    "DescripcionESP":"Suazilandia",
    "DescripcionING":"Swaziland",
    "Continente":5
  },
  {
    "ISO3166A2":"SE",
    "ISO3166A3":"SWE",
    "ISO3166N3":752,
    "latitude":62,
    "longitude":15,
    "DescripcionESP":"Suecia",
    "DescripcionING":"Sweden",
    "Continente":3
  },
  {
    "ISO3166A2":"CH",
    "ISO3166A3":"CHE",
    "ISO3166N3":756,
    "latitude":47,
    "longitude":8,
    "DescripcionESP":"Suiza",
    "DescripcionING":"Switzerland",
    "Continente":3
  },
  {
    "ISO3166A2":"SY",
    "ISO3166A3":"SYR",
    "ISO3166N3":760,
    "latitude":35,
    "longitude":38,
    "DescripcionESP":"Siria",
    "DescripcionING":"Syrian Arab Republic",
    "Continente":4
  },
  {
    "ISO3166A2":"TW",
    "ISO3166A3":"TWN",
    "ISO3166N3":158,
    "latitude":23.5,
    "longitude":121,
    "DescripcionESP":"Taipei, China",
    "DescripcionING":"Taipei, China",
    "Continente":4
  },
  {
    "ISO3166A2":"TJ",
    "ISO3166A3":"TJK",
    "ISO3166N3":762,
    "latitude":39,
    "longitude":71,
    "DescripcionESP":"Tajikistan",
    "DescripcionING":"Tajikistan",
    "Continente":4
  },
  {
    "ISO3166A2":"TZ",
    "ISO3166A3":"TZA",
    "ISO3166N3":834,
    "latitude":-6,
    "longitude":35,
    "DescripcionESP":"Tanzania",
    "DescripcionING":"Tanzania, United Republic of",
    "Continente":5
  },
  {
    "ISO3166A2":"TH",
    "ISO3166A3":"THA",
    "ISO3166N3":764,
    "latitude":15,
    "longitude":100,
    "DescripcionESP":"Tailandia",
    "DescripcionING":"Thailand",
    "Continente":4
  },
  {
    "ISO3166A2":"TG",
    "ISO3166A3":"TGO",
    "ISO3166N3":768,
    "latitude":8,
    "longitude":1.16666666667,
    "DescripcionESP":"Togo",
    "DescripcionING":"Togo",
    "Continente":5
  },
  {
    "ISO3166A2":"TK",
    "ISO3166A3":"TKL",
    "ISO3166N3":772,
    "latitude":-9,
    "longitude":-172,
    "DescripcionESP":"Tokelau",
    "DescripcionING":"Tokelau",
    "Continente":6
  },
  {
    "ISO3166A2":"TO",
    "ISO3166A3":"TON",
    "ISO3166N3":776,
    "latitude":-20,
    "longitude":-175,
    "DescripcionESP":"Tonga",
    "DescripcionING":"Tonga",
    "Continente":5
  },
  {
    "ISO3166A2":"TT",
    "ISO3166A3":"TTO",
    "ISO3166N3":780,
    "latitude":11,
    "longitude":-61,
    "DescripcionESP":"Trinidad y Tobago",
    "DescripcionING":"Trinidad and Tobago",
    "Continente":1
  },
  {
    "ISO3166A2":"TN",
    "ISO3166A3":"TUN",
    "ISO3166N3":788,
    "latitude":34,
    "longitude":9,
    "DescripcionESP":"Tunez",
    "DescripcionING":"Tunisia",
    "Continente":5
  },
  {
    "ISO3166A2":"TR",
    "ISO3166A3":"TUR",
    "ISO3166N3":792,
    "latitude":39,
    "longitude":35,
    "DescripcionESP":"Turquia",
    "DescripcionING":"Turkey",
    "Continente":3
  },
  {
    "ISO3166A2":"TM",
    "ISO3166A3":"TKM",
    "ISO3166N3":795,
    "latitude":40,
    "longitude":60,
    "DescripcionESP":"Turkmenia",
    "DescripcionING":"Turkmenistan",
    "Continente":4
  },
  {
    "ISO3166A2":"TC",
    "ISO3166A3":"TCA",
    "ISO3166N3":796,
    "latitude":21.75,
    "longitude":-71.5833333333,
    "DescripcionESP":"Turcas y Caico",
    "DescripcionING":"Turks and Caicos Islands",
    "Continente":1
  },
  {
    "ISO3166A2":"TV",
    "ISO3166A3":"TUV",
    "ISO3166N3":798,
    "latitude":-8,
    "longitude":178,
    "DescripcionESP":"Tuvalu",
    "DescripcionING":"Tuvalu",
    "Continente":2
  },
  {
    "ISO3166A2":"UG",
    "ISO3166A3":"UGA",
    "ISO3166N3":800,
    "latitude":1,
    "longitude":32,
    "DescripcionESP":"Uganda",
    "DescripcionING":"Uganda",
    "Continente":5
  },
  {
    "ISO3166A2":"UA",
    "ISO3166A3":"UKR",
    "ISO3166N3":804,
    "latitude":49,
    "longitude":32,
    "DescripcionESP":"Ucrania",
    "DescripcionING":"Ukraine",
    "Continente":3
  },
  {
    "ISO3166A2":"AE",
    "ISO3166A3":"ARE",
    "ISO3166N3":784,
    "latitude":24,
    "longitude":54,
    "DescripcionESP":"Emir. de Arabia",
    "DescripcionING":"United Arab Emirates",
    "Continente":4
  },
  {
    "ISO3166A2":"GB",
    "ISO3166A3":"GBR",
    "ISO3166N3":826,
    "latitude":54,
    "longitude":-2,
    "DescripcionESP":"Reino Unido",
    "DescripcionING":"United Kingdom",
    "Continente":3
  },
  {
    "ISO3166A2":"US",
    "ISO3166A3":"USA",
    "ISO3166N3":840,
    "latitude":38,
    "longitude":-97,
    "DescripcionESP":"Estados Unidos",
    "DescripcionING":"United States",
    "Continente":1
  },
  {
    "ISO3166A2":"UY",
    "ISO3166A3":"URY",
    "ISO3166N3":858,
    "latitude":-33,
    "longitude":-56,
    "DescripcionESP":"Uruguay",
    "DescripcionING":"Uruguay",
    "Continente":1
  },
  {
    "ISO3166A2":"UZ",
    "ISO3166A3":"UZB",
    "ISO3166N3":860,
    "latitude":41,
    "longitude":64,
    "DescripcionESP":"Uzberistan",
    "DescripcionING":"Uzbekistan",
    "Continente":4
  },
  {
    "ISO3166A2":"VU",
    "ISO3166A3":"VUT",
    "ISO3166N3":548,
    "latitude":-16,
    "longitude":167,
    "DescripcionESP":"Vanuatu",
    "DescripcionING":"Vanuatu",
    "Continente":2
  },
  {
    "ISO3166A2":"VE",
    "ISO3166A3":"VEN",
    "ISO3166N3":862,
    "latitude":8,
    "longitude":-66,
    "DescripcionESP":"Venezuela",
    "DescripcionING":"Venezuela",
    "Continente":1
  },
  {
    "ISO3166A2":"VN",
    "ISO3166A3":"VNM",
    "ISO3166N3":704,
    "latitude":16.1666666667,
    "longitude":107.833333333,
    "DescripcionESP":"Vietnam",
    "DescripcionING":"Vietnam",
    "Continente":4
  },
  {
    "ISO3166A2":"VG",
    "ISO3166A3":"VGB",
    "ISO3166N3":92,
    "latitude":18.5,
    "longitude":-64.5,
    "DescripcionESP":"Virgenes Brit.",
    "DescripcionING":"Virgin Islands (british)",
    "Continente":1
  },
  {
    "ISO3166A2":"VI",
    "ISO3166A3":"VIR",
    "ISO3166N3":850,
    "latitude":18.3333333333,
    "longitude":-64.8333333333,
    "DescripcionESP":"Virgenes",
    "DescripcionING":"Virgenes",
    "Continente":1
  },
  {
    "ISO3166A2":"WF",
    "ISO3166A3":"WLF",
    "ISO3166N3":876,
    "latitude":-13.3,
    "longitude":-176.2,
    "DescripcionESP":"Wallis y futun",
    "DescripcionING":"Wallis and futuna islands",
    "Continente":2
  },
  {
    "ISO3166A2":"YE",
    "ISO3166A3":"YEM",
    "ISO3166N3":887,
    "latitude":15,
    "longitude":48,
    "DescripcionESP":"Yemen rep.arabe",
    "DescripcionING":"Yemen",
    "Continente":4
  },
  {
    "ISO3166A2":"ZM",
    "ISO3166A3":"ZMB",
    "ISO3166N3":894,
    "latitude":-15,
    "longitude":30,
    "DescripcionESP":"Zambia",
    "DescripcionING":"Zambia",
    "Continente":5
  },
  {
    "ISO3166A2":"ZW",
    "ISO3166A3":"ZWE",
    "ISO3166N3":716,
    "latitude":-20,
    "longitude":30,
    "DescripcionESP":"Zimbabwe",
    "DescripcionING":"Zimbabwe",
    "Continente":5
  }
]